strdes/__init__.py
strdes/des.py
strdes-0.0.1.dist-info/LICENSE
strdes-0.0.1.dist-info/METADATA
strdes-0.0.1.dist-info/WHEEL
strdes-0.0.1.dist-info/top_level.txt
strdes-0.0.1.dist-info/RECORD
