Metadata-Version: 2.1
Name: strdes
Version: 0.0.1
Summary: A string encrypt and decrypt library
Home-page: https://github.com/tootal/strdes
Author: tootal
Author-email: tootal@yeah.net
License: UNKNOWN
Platform: UNKNOWN
Classifier: Programming Language :: Python :: 3
Classifier: License :: OSI Approved :: MIT License
Classifier: Operating System :: OS Independent
Requires-Python: >=3.6
